docs/conf.py
kececilayout/__init__.py
kececilayout/_version.py
kececilayout/kececi_layout.py
kececilayout-0.6.0.dist-info/licenses/LICENSE
tests/test_sample.py
kececilayout-0.6.0.dist-info/METADATA
kececilayout-0.6.0.dist-info/WHEEL
kececilayout-0.6.0.dist-info/top_level.txt
kececilayout-0.6.0.dist-info/RECORD
