Metadata-Version: 2.4
Name: kececilayout
Version: 0.6.0
Summary: Çeşitli graf kütüphaneleri için sıralı-zigzag yerleşimleri sağlayan bir Python paketi.
Home-page: https://github.com/WhiteSymmetry/kececilayout
Author: Mehmet Keçeci
Author-email: Mehmet Keçeci <mkececi@yaani.com>
Maintainer: Mehmet Keçeci
Maintainer-email: bilginomi@yaani.com
License:                     GNU AFFERO GENERAL PUBLIC LICENSE
Project-URL: Homepage, https://github.com/WhiteSymmetry/kececilayout
Project-URL: Bug Tracker, https://github.com/WhiteSymmetry/kececilayout/issues
Classifier: Programming Language :: Python :: 3
Classifier: Operating System :: OS Independent
Classifier: Intended Audience :: Science/Research
Classifier: Topic :: Scientific/Engineering :: Visualization
Requires-Python: >=3.11
License-File: LICENSE
Requires-Dist: cairocffi
Requires-Dist: networkx
Requires-Dist: matplotlib
Requires-Dist: numpy
Provides-Extra: test
Requires-Dist: pytest; extra == "test"
Requires-Dist: pytest-cov; extra == "test"
Requires-Dist: pytest-mock; extra == "test"
Requires-Dist: ruff; extra == "test"
Requires-Dist: python-igraph; extra == "test"
Requires-Dist: python-louvain; extra == "test"
Requires-Dist: rustworkx; extra == "test"
Requires-Dist: networkit; extra == "test"
Requires-Dist: graphillion; extra == "test"
Requires-Dist: graph-tool; extra == "test"
Requires-Dist: numba; extra == "test"
Dynamic: author
Dynamic: home-page
Dynamic: license-file
Dynamic: maintainer
Dynamic: maintainer-email
Dynamic: requires-python
